Workbook

Sheet Dashboard
B2: CoachAndTrack — Monthly Earnings Calculator
B4: =IFERROR('Trainer Data'!D12+'Trainer Data'!E12,0) -> 0 | D4: =IFERROR('Trainer Data'!E12,0) -> 0 | F4: =IFERROR('Trainer Data'!G12,0) -> 0 | G4: =IFERROR('Trainer Data'!H12,0) -> 0
B10: Total Members | D10: Gross Revenue ($) | F10: Platform (30%) | G10: Trainer Pool (70%)
B11: Trainer Payout Summary — Current Month
B13: Trainer Name | C13: Specialty | D13: Members | E13: % of Pool | F13: Gross Payout ($) | G13: Status
B14: ='Trainer Data'!B7 -> Revenue Share — Trainer (%) | C14: ='Trainer Data'!C7 -> 0 | D14: =IFERROR('Trainer Data'!D7,0) -> 0.7 | E14: =IFERROR('Trainer Data'!E7,"-") -> 0 | F14: =IFERROR('Trainer Data'!F7,0) -> 0 | G14: =IFERROR(IF('Trainer Data'!D7>0,"✅ Active","—"),"-") -> ✅ Active
B15: ='Trainer Data'!B8 -> Revenue Share — Platform (%) | C15: ='Trainer Data'!C8 -> 0 | D15: =IFERROR('Trainer Data'!D8,0) -> 0.3 | E15: =IFERROR('Trainer Data'!E8,"-") -> 0 | F15: =IFERROR('Trainer Data'!F8,0) -> 0 | G15: =IFERROR(IF('Trainer Data'!D8>0,"✅ Active","—"),"-") -> ✅ Active
B16: ='Trainer Data'!B9 -> Stripe Processing Fee (%) | C16: ='Trainer Data'!C9 -> 0 | D16: =IFERROR('Trainer Data'!D9,0) -> 0.03 | E16: =IFERROR('Trainer Data'!E9,"-") -> 0 | F16: =IFERROR('Trainer Data'!F9,0) -> 0 | G16: =IFERROR(IF('Trainer Data'!D9>0,"✅ Active","—"),"-") -> ✅ Active
B17: ='Trainer Data'!B10 -> 0 | C17: ='Trainer Data'!C10 -> 0 | D17: =IFERROR('Trainer Data'!D10,0) -> 0 | E17: =IFERROR('Trainer Data'!E10,"-") -> 0 | F17: =IFERROR('Trainer Data'!F10,0) -> 0 | G17: =IFERROR(IF('Trainer Data'!D10>0,"✅ Active","—"),"-") -> —
B18: ='Trainer Data'!B11 -> TOTALS (auto-calculated) | C18: ='Trainer Data'!C11 -> 0 | D18: =IFERROR('Trainer Data'!D11,0) -> Total Members | E18: =IFERROR('Trainer Data'!E11,"-") -> Gross Revenue | F18: =IFERROR('Trainer Data'!F11,0) -> Net Revenue | G18: =IFERROR(IF('Trainer Data'!D11>0,"✅ Active","—"),"-") -> ✅ Active
B19: ='Trainer Data'!B12 -> This Month | C19: ='Trainer Data'!C12 -> 0 | D19: =IFERROR('Trainer Data'!D12,0) -> 0 | E19: =IFERROR('Trainer Data'!E12,"-") -> 0 | F19: =IFERROR('Trainer Data'!F12,0) -> 0 | G19: =IFERROR(IF('Trainer Data'!D12>0,"✅ Active","—"),"-") -> —
B20: ='Trainer Data'!B13 -> 0 | C20: ='Trainer Data'!C13 -> 0 | D20: =IFERROR('Trainer Data'!D13,0) -> 0 | E20: =IFERROR('Trainer Data'!E13,"-") -> 0 | F20: =IFERROR('Trainer Data'!F13,0) -> 0 | G20: =IFERROR(IF('Trainer Data'!D13>0,"✅ Active","—"),"-") -> —
B21: ='Trainer Data'!B14 -> Trainer Roster — Enter trainer details below | C21: ='Trainer Data'!C14 -> 0 | D21: =IFERROR('Trainer Data'!D14,0) -> 0 | E21: =IFERROR('Trainer Data'!E14,"-") -> 0 | F21: =IFERROR('Trainer Data'!F14,0) -> 0 | G21: =IFERROR(IF('Trainer Data'!D14>0,"✅ Active","—"),"-") -> —
B22: ='Trainer Data'!B15 -> Trainer Name | C22: ='Trainer Data'!C15 -> Specialty | D22: =IFERROR('Trainer Data'!D15,0) -> Pro Members | E22: =IFERROR('Trainer Data'!E15,"-") -> Elite Members | F22: =IFERROR('Trainer Data'!F15,0) -> % of Pool | G22: =IFERROR(IF('Trainer Data'!D15>0,"✅ Active","—"),"-") -> ✅ Active
B23: ='Trainer Data'!B16 -> Marcus Rivera | C23: ='Trainer Data'!C16 -> Strength & Conditioning | D23: =IFERROR('Trainer Data'!D16,0) -> 0 | E23: =IFERROR('Trainer Data'!E16,"-") -> 0 | F23: =IFERROR('Trainer Data'!F16,0) -> 0 | G23: =IFERROR(IF('Trainer Data'!D16>0,"✅ Active","—"),"-") -> —
B24: TOTAL | D24: =IFERROR(SUM(D14:D23),0) -> 1.03 | E24: =IFERROR(SUM(E14:E23),0) -> 0 | F24: =IFERROR(SUM(F14:F23),0) -> 0
B25: ⚠️ All figures are estimates. Stripe processing fees (~3%) are deducted before the revenue split. Verify totals before issuing payments.

Sheet Trainer Data
B2: CoachAndTrack — Trainer Data & Assumptions
B4: Platform Assumptions (Blue = edit these cells)
B5: Pro Plan Monthly Price ($) | D5: 14
B6: Elite Plan Monthly Price ($) | D6: 29
B7: Revenue Share — Trainer (%) | D7: 0.7
B8: Revenue Share — Platform (%) | D8: =1-D7 -> 0.3
B9: Stripe Processing Fee (%) | D9: 0.03
B11: TOTALS (auto-calculated) | D11: Total Members | E11: Gross Revenue | F11: Net Revenue | G11: Platform Keeps | H11: Trainer Pool
B12: This Month | D12: =IFERROR(SUM(D7:D16),0) -> 0 | E12: =IFERROR(D12*D5,0) -> 0 | F12: =IFERROR(E12*(1-D9),0) -> 0 | G12: =IFERROR(F12*D8,0) -> 0 | H12: =IFERROR(F12*D7,0) -> 0
B14: Trainer Roster — Enter trainer details below
B15: Trainer Name | C15: Specialty | D15: Pro Members | E15: Elite Members | F15: % of Pool | G15: Gross Payout ($) | H15: Notes
B16: Marcus Rivera | C16: Strength & Conditioning | D16: 0 | E16: 0 | F16: =IFERROR((D16+E16)/(SUM($D$16:$D$25)+SUM($E$16:$E$25)),0) -> 0 | G16: =IFERROR($H$12*F16,0) -> 0
B17: Sofia Chen | C17: Yoga & Mobility | D17: 0 | E17: 0 | F17: =IFERROR((D17+E17)/(SUM($D$16:$D$25)+SUM($E$16:$E$25)),0) -> 0 | G17: =IFERROR($H$12*F17,0) -> 0
B18: James Okafor | C18: HIIT & Cardio | D18: 0 | E18: 0 | F18: =IFERROR((D18+E18)/(SUM($D$16:$D$25)+SUM($E$16:$E$25)),0) -> 0 | G18: =IFERROR($H$12*F18,0) -> 0
B19: Priya Patel | C19: Nutrition & Wellness | D19: 0 | E19: 0 | F19: =IFERROR((D19+E19)/(SUM($D$16:$D$25)+SUM($E$16:$E$25)),0) -> 0 | G19: =IFERROR($H$12*F19,0) -> 0
B20: Tyler Brooks | C20: Functional Fitness | D20: 0 | E20: 0 | F20: =IFERROR((D20+E20)/(SUM($D$16:$D$25)+SUM($E$16:$E$25)),0) -> 0 | G20: =IFERROR($H$12*F20,0) -> 0
D21: 0 | E21: 0 | F21: =IFERROR((D21+E21)/(SUM($D$16:$D$25)+SUM($E$16:$E$25)),0) -> 0 | G21: =IFERROR($H$12*F21,0) -> 0
D22: 0 | E22: 0 | F22: =IFERROR((D22+E22)/(SUM($D$16:$D$25)+SUM($E$16:$E$25)),0) -> 0 | G22: =IFERROR($H$12*F22,0) -> 0
D23: 0 | E23: 0 | F23: =IFERROR((D23+E23)/(SUM($D$16:$D$25)+SUM($E$16:$E$25)),0) -> 0 | G23: =IFERROR($H$12*F23,0) -> 0
D24: 0 | E24: 0 | F24: =IFERROR((D24+E24)/(SUM($D$16:$D$25)+SUM($E$16:$E$25)),0) -> 0 | G24: =IFERROR($H$12*F24,0) -> 0
D25: 0 | E25: 0 | F25: =IFERROR((D25+E25)/(SUM($D$16:$D$25)+SUM($E$16:$E$25)),0) -> 0 | G25: =IFERROR($H$12*F25,0) -> 0
B26: TOTALS | D26: =SUM(D16:D25) -> 0 | E26: =SUM(E16:E25) -> 0 | F26: =SUM(F16:F25) -> 0 | G26: =SUM(G16:G25) -> 0
B28: Color Legend:
B29: Blue text / cells = Input values you enter manually | E29: Black text = Formulas (auto-calculated) | G29: Green cells = Payout results

Sheet Payout History
B2: CoachAndTrack — Payout History Log
B4: Month | C4: Trainer Name | D4: Members | E4: % of Pool | F4: Gross Payout ($) | G4: Payment Date | H4: Payment Status
B5: March 2026 | C5: Marcus Rivera | D5: 1 | E5: 0.2 | F5: 0 | H5: Pending
B6: March 2026 | C6: Sofia Chen | D6: 1 | E6: 0.2 | F6: 0 | H6: Pending
B7: March 2026 | C7: James Okafor | D7: 1 | E7: 0.2 | F7: 0 | H7: Pending
B8: March 2026 | C8: Priya Patel | D8: 0 | E8: 0 | F8: 0 | H8: N/A
B9: March 2026 | C9: Tyler Brooks | D9: 0 | E9: 0 | F9: 0 | H9: N/A
B11: 📋 Each month, copy trainer payout results from the Trainer Data sheet into this log. Update Payment Date and Status after each payout is sent.

Sheet Example Scenarios
B2: CoachAndTrack — Earnings Scenarios & Examples
B4: SCENARIO 1: Launch Month (3 Pro members, 6 trainers)
B5: Pro Members | E5: 3
B6: Elite Members | E6: 0
B7: Gross Revenue | E7: $42.00
B8: Stripe Fees (3%) | E8: ($1.26)
B9: Net Revenue | E9: $40.74
B10: Platform Keeps (30%) | E10: ($12.22)
B11: Trainer Pool (70%) | E11: $28.52
B12: Active Trainers | E12: 3 of 6
B13: Avg Payout per Active Trainer | E13: $9.51
B16: SCENARIO 2: Growing (20 Pro + 5 Elite, 6 trainers)
B17: Pro Members | E17: 20
B18: Elite Members | E18: 5
B19: Gross Revenue | E19: $425.00
B20: Stripe Fees (3%) | E20: ($12.75)
B21: Net Revenue | E21: $412.25
B22: Platform Keeps (30%) | E22: ($123.68)
B23: Trainer Pool (70%) | E23: $288.58
B24: Active Trainers | E24: 6 of 6
B25: Avg Payout per Active Trainer | E25: $48.10
B28: SCENARIO 3: Established (100 Pro + 30 Elite, 10 trainers)
B29: Pro Members | E29: 100
B30: Elite Members | E30: 30
B31: Gross Revenue | E31: $2,270.00
B32: Stripe Fees (3%) | E32: ($68.10)
B33: Net Revenue | E33: $2,201.90
B34: Platform Keeps (30%) | E34: ($660.57)
B35: Trainer Pool (70%) | E35: $1,541.33
B36: Active Trainers | E36: 10 of 10
B37: Avg Payout per Active Trainer | E37: $154.13
B40: 💡 Tip: To earn $1,000/month in the Trainer Pool, CoachAndTrack needs approximately 72 Pro members or 35 Elite members.
